README.md
setup.py
rankum/__init__.py
rankum/diversifiers.py
rankum/exceptions.py
rankum/models.py
rankum/readers.py
rankum.egg-info/PKG-INFO
rankum.egg-info/SOURCES.txt
rankum.egg-info/dependency_links.txt
rankum.egg-info/not-zip-safe
rankum.egg-info/top_level.txt