Metadata-Version: 1.0
Name: rankum
Version: 0.1
Summary: Search Rank experimentation in python
Home-page: UNKNOWN
Author: UNKNOWN
Author-email: UNKNOWN
License: UNKNOWN
Platform: UNKNOWN
